<Annotation><filename>0000006028</filename><size><width>1280</width><height>720</height><depth>3</depth></size><object><name>fire</name><pose>Unspecified</pose><truncated>0</truncated><difficult>0</difficult><bndbox><xmin>421</xmin><ymin>159</ymin><xmax>481</xmax><ymax>243</ymax></bndbox></object><object><name>fire</name><pose>Unspecified</pose><truncated>0</truncated><difficult>0</difficult><bndbox><xmin>77</xmin><ymin>206</ymin><xmax>182</xmax><ymax>275</ymax></bndbox></object><object><name>fire</name><pose>Unspecified</pose><truncated>0</truncated><difficult>0</difficult><bndbox><xmin>320</xmin><ymin>93</ymin><xmax>404</xmax><ymax>170</ymax></bndbox></object></Annotation>