<Annotation><filename>0000004208</filename><size><width>1280</width><height>720</height><depth>3</depth></size><object><name>fire</name><pose>Unspecified</pose><truncated>0</truncated><difficult>0</difficult><bndbox><xmin>152</xmin><ymin>277</ymin><xmax>2000</xmax><ymax>2916</ymax></bndbox></object><object><name>fire</name><pose>Unspecified</pose><truncated>0</truncated><difficult>0</difficult><bndbox><xmin>402</xmin><ymin>50</ymin><xmax>1759</xmax><ymax>1396</ymax></bndbox></object></Annotation>