<Annotation><filename>0000001756</filename><size><width>1280</width><height>720</height><depth>3</depth></size><object><name>smoke</name><pose>Unspecified</pose><truncated>0</truncated><difficult>0</difficult><bndbox><xmin>6</xmin><ymin>1</ymin><xmax>126</xmax><ymax>401</ymax></bndbox></object><object><name>smoke</name><pose>Unspecified</pose><truncated>0</truncated><difficult>0</difficult><bndbox><xmin>135</xmin><ymin>130</ymin><xmax>259</xmax><ymax>505</ymax></bndbox></object><object><name>smoke</name><pose>Unspecified</pose><truncated>0</truncated><difficult>0</difficult><bndbox><xmin>330</xmin><ymin>103</ymin><xmax>585</xmax><ymax>339</ymax></bndbox></object><object><name>smoke</name><pose>Unspecified</pose><truncated>0</truncated><difficult>0</difficult><bndbox><xmin>289</xmin><ymin>470</ymin><xmax>547</xmax><ymax>556</ymax></bndbox></object><object><name>smoke</name><pose>Unspecified</pose><truncated>0</truncated><difficult>0</difficult><bndbox><xmin>291</xmin><ymin>342</ymin><xmax>380</xmax><ymax>450</ymax></bndbox></object><object><name>smoke</name><pose>Unspecified</pose><truncated>0</truncated><difficult>0</difficult><bndbox><xmin>381</xmin><ymin>348</ymin><xmax>561</xmax><ymax>477</ymax></bndbox></object></Annotation>