<Annotation><filename>0000004300</filename><size><width>1280</width><height>720</height><depth>3</depth></size><object><name>fire</name><pose>Unspecified</pose><truncated>0</truncated><difficult>0</difficult><bndbox><xmin>708</xmin><ymin>487</ymin><xmax>3849</xmax><ymax>2890</ymax></bndbox></object><object><name>fire</name><pose>Unspecified</pose><truncated>0</truncated><difficult>0</difficult><bndbox><xmin>1002</xmin><ymin>693</ymin><xmax>1361</xmax><ymax>1335</ymax></bndbox></object></Annotation>