<Annotation><filename>0000014155</filename><size><width>1280</width><height>720</height><depth>3</depth></size><object><name>smoke</name><pose>Unspecified</pose><truncated>0</truncated><difficult>0</difficult><bndbox><xmin>7</xmin><ymin>93</ymin><xmax>146</xmax><ymax>175</ymax></bndbox></object><object><name>smoke</name><pose>Unspecified</pose><truncated>0</truncated><difficult>0</difficult><bndbox><xmin>345</xmin><ymin>118</ymin><xmax>419</xmax><ymax>226</ymax></bndbox></object><object><name>smoke</name><pose>Unspecified</pose><truncated>0</truncated><difficult>0</difficult><bndbox><xmin>133</xmin><ymin>114</ymin><xmax>344</xmax><ymax>212</ymax></bndbox></object><object><name>smoke</name><pose>Unspecified</pose><truncated>0</truncated><difficult>0</difficult><bndbox><xmin>147</xmin><ymin>29</ymin><xmax>332</xmax><ymax>113</ymax></bndbox></object><object><name>smoke</name><pose>Unspecified</pose><truncated>0</truncated><difficult>0</difficult><bndbox><xmin>343</xmin><ymin>10</ymin><xmax>490</xmax><ymax>116</ymax></bndbox></object><object><name>smoke</name><pose>Unspecified</pose><truncated>0</truncated><difficult>0</difficult><bndbox><xmin>255</xmin><ymin>215</ymin><xmax>432</xmax><ymax>349</ymax></bndbox></object></Annotation>