<Annotation><filename>0000014114</filename><size><width>1280</width><height>720</height><depth>3</depth></size><object><name>smoke</name><pose>Unspecified</pose><truncated>0</truncated><difficult>0</difficult><bndbox><xmin>87</xmin><ymin>1</ymin><xmax>324</xmax><ymax>300</ymax></bndbox></object><object><name>smoke</name><pose>Unspecified</pose><truncated>0</truncated><difficult>0</difficult><bndbox><xmin>22</xmin><ymin>117</ymin><xmax>51</xmax><ymax>143</ymax></bndbox></object><object><name>smoke</name><pose>Unspecified</pose><truncated>0</truncated><difficult>0</difficult><bndbox><xmin>20</xmin><ymin>264</ymin><xmax>118</xmax><ymax>315</ymax></bndbox></object><object><name>smoke</name><pose>Unspecified</pose><truncated>0</truncated><difficult>0</difficult><bndbox><xmin>149</xmin><ymin>288</ymin><xmax>215</xmax><ymax>339</ymax></bndbox></object><object><name>smoke</name><pose>Unspecified</pose><truncated>0</truncated><difficult>0</difficult><bndbox><xmin>51</xmin><ymin>122</ymin><xmax>124</xmax><ymax>263</ymax></bndbox></object></Annotation>