<Annotation><filename>0000000310</filename><size><width>1280</width><height>720</height><depth>3</depth></size><object><name>smoke</name><pose>Unspecified</pose><truncated>0</truncated><difficult>0</difficult><bndbox><xmin>526</xmin><ymin>105</ymin><xmax>603</xmax><ymax>358</ymax></bndbox></object><object><name>smoke</name><pose>Unspecified</pose><truncated>0</truncated><difficult>0</difficult><bndbox><xmin>445</xmin><ymin>242</ymin><xmax>523</xmax><ymax>339</ymax></bndbox></object><object><name>smoke</name><pose>Unspecified</pose><truncated>0</truncated><difficult>0</difficult><bndbox><xmin>20</xmin><ymin>2</ymin><xmax>398</xmax><ymax>141</ymax></bndbox></object><object><name>smoke</name><pose>Unspecified</pose><truncated>0</truncated><difficult>0</difficult><bndbox><xmin>395</xmin><ymin>23</ymin><xmax>528</xmax><ymax>240</ymax></bndbox></object></Annotation>