<Annotation><filename>0000009459</filename><size><width>1280</width><height>720</height><depth>3</depth></size><object><name>fire</name><pose>Unspecified</pose><truncated>0</truncated><difficult>0</difficult><bndbox><xmin>47</xmin><ymin>103</ymin><xmax>104</xmax><ymax>130</ymax></bndbox></object><object><name>fire</name><pose>Unspecified</pose><truncated>0</truncated><difficult>0</difficult><bndbox><xmin>53</xmin><ymin>56</ymin><xmax>122</xmax><ymax>96</ymax></bndbox></object><object><name>fire</name><pose>Unspecified</pose><truncated>0</truncated><difficult>0</difficult><bndbox><xmin>113</xmin><ymin>108</ymin><xmax>152</xmax><ymax>134</ymax></bndbox></object><object><name>fire</name><pose>Unspecified</pose><truncated>0</truncated><difficult>0</difficult><bndbox><xmin>161</xmin><ymin>45</ymin><xmax>241</xmax><ymax>129</ymax></bndbox></object></Annotation>