<Annotation><filename>0000005023</filename><size><width>1280</width><height>720</height><depth>3</depth></size><object><name>smoke</name><pose>Unspecified</pose><truncated>0</truncated><difficult>0</difficult><bndbox><xmin>1</xmin><ymin>4</ymin><xmax>44</xmax><ymax>91</ymax></bndbox></object><object><name>smoke</name><pose>Unspecified</pose><truncated>0</truncated><difficult>0</difficult><bndbox><xmin>329</xmin><ymin>155</ymin><xmax>382</xmax><ymax>188</ymax></bndbox></object><object><name>fire</name><pose>Unspecified</pose><truncated>0</truncated><difficult>0</difficult><bndbox><xmin>375</xmin><ymin>199</ymin><xmax>393</xmax><ymax>211</ymax></bndbox></object><object><name>smoke</name><pose>Unspecified</pose><truncated>0</truncated><difficult>0</difficult><bndbox><xmin>194</xmin><ymin>21</ymin><xmax>392</xmax><ymax>191</ymax></bndbox></object><object><name>smoke</name><pose>Unspecified</pose><truncated>0</truncated><difficult>0</difficult><bndbox><xmin>8</xmin><ymin>111</ymin><xmax>137</xmax><ymax>186</ymax></bndbox></object></Annotation>