<Annotation><filename>0000006171</filename><size><width>1280</width><height>720</height><depth>3</depth></size><object><name>fire</name><pose>Unspecified</pose><truncated>0</truncated><difficult>0</difficult><bndbox><xmin>820</xmin><ymin>432</ymin><xmax>899</xmax><ymax>546</ymax></bndbox></object><object><name>fire</name><pose>Unspecified</pose><truncated>0</truncated><difficult>0</difficult><bndbox><xmin>395</xmin><ymin>137</ymin><xmax>497</xmax><ymax>267</ymax></bndbox></object><object><name>fire</name><pose>Unspecified</pose><truncated>0</truncated><difficult>0</difficult><bndbox><xmin>553</xmin><ymin>147</ymin><xmax>703</xmax><ymax>292</ymax></bndbox></object></Annotation>