<Annotation><filename>0000002124</filename><size><width>1280</width><height>720</height><depth>3</depth></size><object><name>smoke</name><pose>Unspecified</pose><truncated>0</truncated><difficult>0</difficult><bndbox><xmin>1328</xmin><ymin>225</ymin><xmax>1541</xmax><ymax>346</ymax></bndbox></object><object><name>smoke</name><pose>Unspecified</pose><truncated>0</truncated><difficult>0</difficult><bndbox><xmin>262</xmin><ymin>1</ymin><xmax>427</xmax><ymax>148</ymax></bndbox></object><object><name>smoke</name><pose>Unspecified</pose><truncated>0</truncated><difficult>0</difficult><bndbox><xmin>706</xmin><ymin>153</ymin><xmax>891</xmax><ymax>350</ymax></bndbox></object><object><name>smoke</name><pose>Unspecified</pose><truncated>0</truncated><difficult>0</difficult><bndbox><xmin>686</xmin><ymin>4</ymin><xmax>1007</xmax><ymax>145</ymax></bndbox></object><object><name>smoke</name><pose>Unspecified</pose><truncated>0</truncated><difficult>0</difficult><bndbox><xmin>1186</xmin><ymin>10</ymin><xmax>1484</xmax><ymax>220</ymax></bndbox></object><object><name>smoke</name><pose>Unspecified</pose><truncated>0</truncated><difficult>0</difficult><bndbox><xmin>1018</xmin><ymin>69</ymin><xmax>1116</xmax><ymax>172</ymax></bndbox></object></Annotation>