<Annotation><filename>0000001950</filename><size><width>1280</width><height>720</height><depth>3</depth></size><object><name>smoke</name><pose>Unspecified</pose><truncated>0</truncated><difficult>0</difficult><bndbox><xmin>233</xmin><ymin>16</ymin><xmax>299</xmax><ymax>115</ymax></bndbox></object><object><name>smoke</name><pose>Unspecified</pose><truncated>0</truncated><difficult>0</difficult><bndbox><xmin>190</xmin><ymin>70</ymin><xmax>239</xmax><ymax>128</ymax></bndbox></object><object><name>smoke</name><pose>Unspecified</pose><truncated>0</truncated><difficult>0</difficult><bndbox><xmin>247</xmin><ymin>105</ymin><xmax>298</xmax><ymax>157</ymax></bndbox></object><object><name>smoke</name><pose>Unspecified</pose><truncated>0</truncated><difficult>0</difficult><bndbox><xmin>150</xmin><ymin>103</ymin><xmax>201</xmax><ymax>159</ymax></bndbox></object></Annotation>