<Annotation><filename>0000003397</filename><size><width>1280</width><height>720</height><depth>3</depth></size><object><name>smoke</name><pose>Unspecified</pose><truncated>0</truncated><difficult>0</difficult><bndbox><xmin>355</xmin><ymin>11</ymin><xmax>529</xmax><ymax>132</ymax></bndbox></object><object><name>smoke</name><pose>Unspecified</pose><truncated>0</truncated><difficult>0</difficult><bndbox><xmin>1</xmin><ymin>192</ymin><xmax>75</xmax><ymax>339</ymax></bndbox></object><object><name>smoke</name><pose>Unspecified</pose><truncated>0</truncated><difficult>0</difficult><bndbox><xmin>17</xmin><ymin>15</ymin><xmax>118</xmax><ymax>69</ymax></bndbox></object></Annotation>