<Annotation><filename>0000003387</filename><size><width>1280</width><height>720</height><depth>3</depth></size><object><name>smoke</name><pose>Unspecified</pose><truncated>0</truncated><difficult>0</difficult><bndbox><xmin>258</xmin><ymin>189</ymin><xmax>952</xmax><ymax>286</ymax></bndbox></object><object><name>smoke</name><pose>Unspecified</pose><truncated>0</truncated><difficult>0</difficult><bndbox><xmin>3</xmin><ymin>185</ymin><xmax>703</xmax><ymax>293</ymax></bndbox></object><object><name>smoke</name><pose>Unspecified</pose><truncated>0</truncated><difficult>0</difficult><bndbox><xmin>1</xmin><ymin>15</ymin><xmax>112</xmax><ymax>191</ymax></bndbox></object><object><name>smoke</name><pose>Unspecified</pose><truncated>0</truncated><difficult>0</difficult><bndbox><xmin>347</xmin><ymin>291</ymin><xmax>701</xmax><ymax>439</ymax></bndbox></object><object><name>smoke</name><pose>Unspecified</pose><truncated>0</truncated><difficult>0</difficult><bndbox><xmin>2</xmin><ymin>27</ymin><xmax>242</xmax><ymax>202</ymax></bndbox></object><object><name>smoke</name><pose>Unspecified</pose><truncated>0</truncated><difficult>0</difficult><bndbox><xmin>265</xmin><ymin>22</ymin><xmax>627</xmax><ymax>193</ymax></bndbox></object><object><name>smoke</name><pose>Unspecified</pose><truncated>0</truncated><difficult>0</difficult><bndbox><xmin>598</xmin><ymin>28</ymin><xmax>960</xmax><ymax>211</ymax></bndbox></object><object><name>smoke</name><pose>Unspecified</pose><truncated>0</truncated><difficult>0</difficult><bndbox><xmin>781</xmin><ymin>304</ymin><xmax>961</xmax><ymax>448</ymax></bndbox></object><object><name>smoke</name><pose>Unspecified</pose><truncated>0</truncated><difficult>0</difficult><bndbox><xmin>7</xmin><ymin>305</ymin><xmax>324</xmax><ymax>448</ymax></bndbox></object></Annotation>