<Annotation><filename>0000001410</filename><size><width>1280</width><height>720</height><depth>3</depth></size><object><name>smoke</name><pose>Unspecified</pose><truncated>0</truncated><difficult>0</difficult><bndbox><xmin>1183</xmin><ymin>442</ymin><xmax>1435</xmax><ymax>701</ymax></bndbox></object><object><name>smoke</name><pose>Unspecified</pose><truncated>0</truncated><difficult>0</difficult><bndbox><xmin>888</xmin><ymin>7</ymin><xmax>1187</xmax><ymax>107</ymax></bndbox></object><object><name>smoke</name><pose>Unspecified</pose><truncated>0</truncated><difficult>0</difficult><bndbox><xmin>939</xmin><ymin>445</ymin><xmax>1145</xmax><ymax>667</ymax></bndbox></object><object><name>smoke</name><pose>Unspecified</pose><truncated>0</truncated><difficult>0</difficult><bndbox><xmin>912</xmin><ymin>312</ymin><xmax>1306</xmax><ymax>435</ymax></bndbox></object><object><name>smoke</name><pose>Unspecified</pose><truncated>0</truncated><difficult>0</difficult><bndbox><xmin>694</xmin><ymin>300</ymin><xmax>864</xmax><ymax>469</ymax></bndbox></object><object><name>smoke</name><pose>Unspecified</pose><truncated>0</truncated><difficult>0</difficult><bndbox><xmin>751</xmin><ymin>104</ymin><xmax>1192</xmax><ymax>309</ymax></bndbox></object><object><name>smoke</name><pose>Unspecified</pose><truncated>0</truncated><difficult>0</difficult><bndbox><xmin>1201</xmin><ymin>8</ymin><xmax>1435</xmax><ymax>280</ymax></bndbox></object></Annotation>