<Annotation><filename>0000012565</filename><size><width>1280</width><height>720</height><depth>3</depth></size><object><name>smoke</name><pose>Unspecified</pose><truncated>0</truncated><difficult>0</difficult><bndbox><xmin>1265</xmin><ymin>787</ymin><xmax>1916</xmax><ymax>1066</ymax></bndbox></object><object><name>smoke</name><pose>Unspecified</pose><truncated>0</truncated><difficult>0</difficult><bndbox><xmin>877</xmin><ymin>478</ymin><xmax>1001</xmax><ymax>788</ymax></bndbox></object><object><name>smoke</name><pose>Unspecified</pose><truncated>0</truncated><difficult>0</difficult><bndbox><xmin>608</xmin><ymin>242</ymin><xmax>747</xmax><ymax>467</ymax></bndbox></object><object><name>smoke</name><pose>Unspecified</pose><truncated>0</truncated><difficult>0</difficult><bndbox><xmin>1439</xmin><ymin>468</ymin><xmax>1838</xmax><ymax>643</ymax></bndbox></object><object><name>smoke</name><pose>Unspecified</pose><truncated>0</truncated><difficult>0</difficult><bndbox><xmin>772</xmin><ymin>6</ymin><xmax>1097</xmax><ymax>448</ymax></bndbox></object><object><name>smoke</name><pose>Unspecified</pose><truncated>0</truncated><difficult>0</difficult><bndbox><xmin>573</xmin><ymin>2</ymin><xmax>767</xmax><ymax>228</ymax></bndbox></object></Annotation>