<Annotation><filename>0000014598</filename><size><width>1280</width><height>720</height><depth>3</depth></size><object><name>smoke</name><pose>Unspecified</pose><truncated>0</truncated><difficult>0</difficult><bndbox><xmin>208</xmin><ymin>6</ymin><xmax>410</xmax><ymax>179</ymax></bndbox></object><object><name>smoke</name><pose>Unspecified</pose><truncated>0</truncated><difficult>0</difficult><bndbox><xmin>399</xmin><ymin>8</ymin><xmax>549</xmax><ymax>198</ymax></bndbox></object><object><name>smoke</name><pose>Unspecified</pose><truncated>0</truncated><difficult>0</difficult><bndbox><xmin>154</xmin><ymin>184</ymin><xmax>254</xmax><ymax>355</ymax></bndbox></object><object><name>smoke</name><pose>Unspecified</pose><truncated>0</truncated><difficult>0</difficult><bndbox><xmin>1</xmin><ymin>4</ymin><xmax>205</xmax><ymax>134</ymax></bndbox></object></Annotation>