<Annotation><filename>0000013924</filename><size><width>1280</width><height>720</height><depth>3</depth></size><object><name>smoke</name><pose>Unspecified</pose><truncated>0</truncated><difficult>0</difficult><bndbox><xmin>134</xmin><ymin>7</ymin><xmax>248</xmax><ymax>241</ymax></bndbox></object><object><name>smoke</name><pose>Unspecified</pose><truncated>0</truncated><difficult>0</difficult><bndbox><xmin>278</xmin><ymin>344</ymin><xmax>608</xmax><ymax>466</ymax></bndbox></object><object><name>smoke</name><pose>Unspecified</pose><truncated>0</truncated><difficult>0</difficult><bndbox><xmin>582</xmin><ymin>570</ymin><xmax>638</xmax><ymax>643</ymax></bndbox></object><object><name>smoke</name><pose>Unspecified</pose><truncated>0</truncated><difficult>0</difficult><bndbox><xmin>252</xmin><ymin>1</ymin><xmax>482</xmax><ymax>340</ymax></bndbox></object><object><name>smoke</name><pose>Unspecified</pose><truncated>0</truncated><difficult>0</difficult><bndbox><xmin>191</xmin><ymin>246</ymin><xmax>267</xmax><ymax>400</ymax></bndbox></object><object><name>smoke</name><pose>Unspecified</pose><truncated>0</truncated><difficult>0</difficult><bndbox><xmin>463</xmin><ymin>459</ymin><xmax>649</xmax><ymax>568</ymax></bndbox></object></Annotation>