<Annotation><filename>0000012964</filename><size><width>1280</width><height>720</height><depth>3</depth></size><object><name>smoke</name><pose>Unspecified</pose><truncated>0</truncated><difficult>0</difficult><bndbox><xmin>272</xmin><ymin>173</ymin><xmax>479</xmax><ymax>265</ymax></bndbox></object><object><name>smoke</name><pose>Unspecified</pose><truncated>0</truncated><difficult>0</difficult><bndbox><xmin>316</xmin><ymin>2</ymin><xmax>509</xmax><ymax>177</ymax></bndbox></object><object><name>smoke</name><pose>Unspecified</pose><truncated>0</truncated><difficult>0</difficult><bndbox><xmin>304</xmin><ymin>266</ymin><xmax>360</xmax><ymax>306</ymax></bndbox></object><object><name>smoke</name><pose>Unspecified</pose><truncated>0</truncated><difficult>0</difficult><bndbox><xmin>248</xmin><ymin>267</ymin><xmax>284</xmax><ymax>305</ymax></bndbox></object></Annotation>