<Annotation><filename>0000009721</filename><size><width>1280</width><height>720</height><depth>3</depth></size><object><name>smoke</name><pose>Unspecified</pose><truncated>0</truncated><difficult>0</difficult><bndbox><xmin>93</xmin><ymin>0</ymin><xmax>145</xmax><ymax>107</ymax></bndbox></object><object><name>fire</name><pose>Unspecified</pose><truncated>0</truncated><difficult>0</difficult><bndbox><xmin>45</xmin><ymin>78</ymin><xmax>93</xmax><ymax>118</ymax></bndbox></object><object><name>fire</name><pose>Unspecified</pose><truncated>0</truncated><difficult>0</difficult><bndbox><xmin>105</xmin><ymin>79</ymin><xmax>154</xmax><ymax>123</ymax></bndbox></object></Annotation>