<Annotation><filename>0000007903</filename><size><width>1280</width><height>720</height><depth>3</depth></size><object><name>fire</name><pose>Unspecified</pose><truncated>0</truncated><difficult>0</difficult><bndbox><xmin>36</xmin><ymin>104</ymin><xmax>63</xmax><ymax>122</ymax></bndbox></object><object><name>fire</name><pose>Unspecified</pose><truncated>0</truncated><difficult>0</difficult><bndbox><xmin>68</xmin><ymin>81</ymin><xmax>98</xmax><ymax>116</ymax></bndbox></object><object><name>fire</name><pose>Unspecified</pose><truncated>0</truncated><difficult>0</difficult><bndbox><xmin>54</xmin><ymin>114</ymin><xmax>79</xmax><ymax>141</ymax></bndbox></object><object><name>fire</name><pose>Unspecified</pose><truncated>0</truncated><difficult>0</difficult><bndbox><xmin>95</xmin><ymin>74</ymin><xmax>120</xmax><ymax>97</ymax></bndbox></object><object><name>fire</name><pose>Unspecified</pose><truncated>0</truncated><difficult>0</difficult><bndbox><xmin>217</xmin><ymin>32</ymin><xmax>253</xmax><ymax>86</ymax></bndbox></object><object><name>fire</name><pose>Unspecified</pose><truncated>0</truncated><difficult>0</difficult><bndbox><xmin>156</xmin><ymin>23</ymin><xmax>192</xmax><ymax>77</ymax></bndbox></object></Annotation>