<Annotation><filename>0000012579</filename><size><width>1280</width><height>720</height><depth>3</depth></size><object><name>smoke</name><pose>Unspecified</pose><truncated>0</truncated><difficult>0</difficult><bndbox><xmin>768</xmin><ymin>383</ymin><xmax>953</xmax><ymax>585</ymax></bndbox></object><object><name>smoke</name><pose>Unspecified</pose><truncated>0</truncated><difficult>0</difficult><bndbox><xmin>661</xmin><ymin>603</ymin><xmax>832</xmax><ymax>794</ymax></bndbox></object></Annotation>